AUTHORS.rst
HISTORY.rst
LICENSE
MANIFEST.in
README.rst
daikon.conf
setup.py
daikon/__init__.py
daikon/config.py
daikon/connection.py
daikon/display.py
daikon/exceptions.py
daikon/main.py
daikon/parser.py
daikon.egg-info/PKG-INFO
daikon.egg-info/SOURCES.txt
daikon.egg-info/dependency_links.txt
daikon.egg-info/entry_points.txt
daikon.egg-info/not-zip-safe
daikon.egg-info/requires.txt
daikon.egg-info/top_level.txt
daikon/managers/__init__.py
daikon/managers/cluster.py
daikon/managers/index.py
daikon/managers/node.py