Metadata-Version: 1.1
Name: daikon
Version: 1.50
Summary: ElasticSearch CLI
Home-page: http://www.github.com/neogenix/daikon
Author: Patrick Ancillotti
Author-email: patrick@eefy.net
License: LICENSE
Platform: UNKNOWN
Classifier: Development Status :: 4 - Beta
Classifier: Programming Language :: Python
